{
  "version": "7",
  "dialect": "postgresql",
  "entries": [
    {
      "idx": 0,
      "version": "7",
      "when": 1772158369112,
      "tag": "0000_milky_shotgun",
      "breakpoints": true
    },
    {
      "idx": 1,
      "version": "7",
      "when": 1772419343026,
      "tag": "0001_tricky_satana",
      "breakpoints": true
    },
    {
      "idx": 2,
      "version": "7",
      "when": 1772647120414,
      "tag": "0002_polite_meggan",
      "breakpoints": true
    },
    {
      "idx": 3,
      "version": "7",
      "when": 1772652027714,
      "tag": "0003_common_maximus",
      "breakpoints": true
    },
    {
      "idx": 4,
      "version": "7",
      "when": 1773609705183,
      "tag": "0004_tough_hedge_knight",
      "breakpoints": true
    },
    {
      "idx": 5,
      "version": "7",
      "when": 1773866423805,
      "tag": "0005_chunky_sally_floyd",
      "breakpoints": true
    },
    {
      "idx": 6,
      "version": "7",
      "when": 1774049121695,
      "tag": "0006_normalize-knowledge",
      "breakpoints": true
    }
  ]
}
